sigmavest/__init__.py
sigmavest/cache/__init__.py
sigmavest/cache/file_cache.py
sigmavest/calc/__init__.py
sigmavest/calc/cagr/__init__.py
sigmavest/calc/cagr/cagr.py
sigmavest/calc/cagr/cli.py
sigmavest/calc/cagr/gui.py
sigmavest/calc/cli.py
sigmavest/cli.py
sigmavest/dependency/__init__.py
sigmavest/dependency/container.py
sigmavest/invest/__init__.py
sigmavest/invest/cli/__init__.py
sigmavest/invest/cli/database.py
sigmavest/invest/cli/magicformula.py
sigmavest/invest/cli/portfolio.py
sigmavest/invest/cli/transaction.py
sigmavest/invest/dependency.py
sigmavest/invest/domain/__init__.py
sigmavest/invest/domain/base.py
sigmavest/invest/domain/portfolio.py
sigmavest/invest/domain/transaction.py
sigmavest/invest/exceptions.py
sigmavest/invest/README.md
sigmavest/invest/repository/__init__.py
sigmavest/invest/repository/db.py
sigmavest/invest/repository/portfolio.py
sigmavest/invest/repository/sell_allocations.py
sigmavest/invest/repository/transaction.py
sigmavest/invest/service/__init__.py
sigmavest/invest/service/database.py
sigmavest/invest/service/portfolio.py
sigmavest/invest/service/requests/__init__.py
sigmavest/invest/service/requests/base.py
sigmavest/invest/service/requests/database.py
sigmavest/invest/service/requests/portfolio.py
sigmavest/invest/service/requests/transaction.py
sigmavest/invest/service/transaction.py
sigmavest/magicformula/__init__.py
sigmavest/magicformula/magic_formula_scraper.py
sigmavest/magicformula/README.md
sigmavest/sec/__init__.py
sigmavest/sec/cli.py
sigmavest/sec/client.py
sigmavest/sec/shortcuts.py
sigmavest/settings.py
sigmavest/stock/__init__.py
sigmavest/stock/magic_formula.py
sigmavest/stock/models.py
sigmavest/stock/repository.py
sigmavest/stock/statement.py
sigmavest/stock/stock.py
sigmavest/utils.py
sigmavest-0.1.4.dist-info/entry_points.txt
sigmavest-0.1.4.dist-info/METADATA
sigmavest-0.1.4.dist-info/WHEEL
sigmavest-0.1.4.dist-info/RECORD
